{
    "products": [{
            "id": 1,
            "name": "ES2015 Template Strings",
            "description": "Template strings are an incredibly useful new feature in ES2015... and you can use them in your Ember apps today! Here are 3 cool things that template strings enable.",
            "price": 40000
        },
        {
            "id": 2,
            "name": "ES2015 Modules",
            "description": "Before modules, javascript code loading was a mess. Now it's pretty amazing.",
            "price": 60000
        },
        {
            "id": 3,
            "name": "ES2015 Modules",
            "description": "Before modules, javascript code loading was a mess. Now it's pretty amazing.",
            "price": 60000
        },
        {
            "id": 4,
            "name": "Creating New Promises",
            "description": "Sometimes you want to start a new promise chain or have greater control over the timing of events. By manually creating a promise, you can do that.",
            "price": 980020
        },
        {
            "id": 6,
            "name": "ES2015 Destructuring",
            "description": "Destructuring is really cool, can save you code, and you’re probably already using a small portion of its power. Learn more about this cool new ES2015 / ES6 feature, including how to destructure deeply nested objects, how to use it with Embers import statement,and how to use it with arrays.",
            "price": 23000000
        },
        {
            "id": 7,
            "name": "ES2016 Decorators",
            "description": "Decorators let you easily and repeatedly add functionality to existing functions. In this episode we go over how to use and create decorators, creating two useful decorators that demonstrate different parts of the API",
            "price": 34502
        }, {
            "id": 8,
            "name": "Apple Watch SR5",
            "description": "Decorators let you easily and repeatedly add functionality to existing functions. In this episode we go over how to use and create decorators, creating two useful decorators that demonstrate different parts of the API",
            "price": 3453302
        },
        {
            "id": 9,
            "name": "Iphone 10",
            "description": "Decorators let you easily and repeatedly add functionality to existing functions. In this episode we go over how to use and create decorators, creating two useful decorators that demonstrate different parts of the API",
            "price": 3455502
        },
        {
            "id": 10,
            "name": "Ipad Air",
            "description": "Decorators let you easily and repeatedly add functionality to existing functions. In this episode we go over how to use and create decorators, creating two useful decorators that demonstrate different parts of the API",
            "price": 34506662
        }
    ]
}